deepfolder/__init__.py
deep_folder-1.0.2.dist-info/LICENSE
deep_folder-1.0.2.dist-info/METADATA
deep_folder-1.0.2.dist-info/WHEEL
deep_folder-1.0.2.dist-info/top_level.txt
deep_folder-1.0.2.dist-info/RECORD
