Metadata-Version: 2.1
Name: deep-folder
Version: 1.0.2
Summary: create or remove a simple folder
Home-page: https://github.com/Sotaneum/deep-folder
Author: sotaneum
Author-email: gnyontu39@gmail.com
License: UNKNOWN
Platform: UNKNOWN
Classifier: Programming Language :: Python :: 3
Classifier: License :: OSI Approved :: MIT License
Classifier: Operating System :: OS Independent
Requires-Python: >=3.6
License-File: LICENSE
